{
  "schemaVersion": 1,
  "rosterId": "transfermarkt_team_3654",
  "teamName": "KALMAR",
  "canonicalTeamName": "Kalmar Fotbollförening",
  "teamType": "club",
  "sourceTeamId": "3654",
  "rosterSource": "current_club_players",
  "rosterConfidence": "HIGH",
  "rosterWarning": null,
  "source": "transfermarkt-datasets",
  "updatedAt": "2026-06-29T11:58:21.303292+00:00",
  "coach": null,
  "players": [
    {
      "source": "transfermarkt-datasets",
      "sourcePlayerId": "836892",
      "name": "Abdi Sabriye",
      "position": "Attack",
      "detailedPosition": "Left Winger",
      "nationality": "Sweden",
      "dateOfBirth": "2002-03-05 00:00:00",
      "age": 24,
      "heightInCm": 175,
      "currentClubName": "Kalmar Fotbollförening",
      "photoUrl": "https://img.a.transfermarkt.technology/portrait/header/default.jpg?lm=1",
      "shirtNumber": null
    },
    {
      "source": "transfermarkt-datasets",
      "sourcePlayerId": "511852",
      "name": "Anthony Olusanya",
      "position": "Attack",
      "detailedPosition": "Centre-Forward",
      "nationality": "Finland",
      "dateOfBirth": "2000-02-01 00:00:00",
      "age": 26,
      "heightInCm": 183,
      "currentClubName": "Kalmar Fotbollförening",
      "photoUrl": "https://img.a.transfermarkt.technology/portrait/header/511852-1623140480.jpg?lm=1",
      "shirtNumber": null
    },
    {
      "source": "transfermarkt-datasets",
      "sourcePlayerId": "796037",
      "name": "Charles Sagoe Jr",
      "position": "Attack",
      "detailedPosition": "Left Winger",
      "nationality": "England",
      "dateOfBirth": "2004-07-24 00:00:00",
      "age": 21,
      "heightInCm": 170,
      "currentClubName": "Kalmar Fotbollförening",
      "photoUrl": "https://img.a.transfermarkt.technology/portrait/header/796037-1688730988.jpg?lm=1",
      "shirtNumber": null
    },
    {
      "source": "transfermarkt-datasets",
      "sourcePlayerId": "1376024",
      "name": "Charlie Rosenqvist",
      "position": "Attack",
      "detailedPosition": "Centre-Forward",
      "nationality": "Sweden",
      "dateOfBirth": "2007-05-01 00:00:00",
      "age": 19,
      "heightInCm": null,
      "currentClubName": "Kalmar Fotbollförening",
      "photoUrl": "https://img.a.transfermarkt.technology/portrait/header/default.jpg?lm=1",
      "shirtNumber": null
    },
    {
      "source": "transfermarkt-datasets",
      "sourcePlayerId": "564453",
      "name": "Emeka Nnamani",
      "position": "Attack",
      "detailedPosition": "Centre-Forward",
      "nationality": "Denmark",
      "dateOfBirth": "2001-11-04 00:00:00",
      "age": 24,
      "heightInCm": 183,
      "currentClubName": "Kalmar Fotbollförening",
      "photoUrl": "https://img.a.transfermarkt.technology/portrait/header/default.jpg?lm=1",
      "shirtNumber": null
    },
    {
      "source": "transfermarkt-datasets",
      "sourcePlayerId": "549405",
      "name": "Malcolm Stolt",
      "position": "Attack",
      "detailedPosition": "Centre-Forward",
      "nationality": "Sweden",
      "dateOfBirth": "2000-12-30 00:00:00",
      "age": 25,
      "heightInCm": 188,
      "currentClubName": "Kalmar Fotbollförening",
      "photoUrl": "https://img.a.transfermarkt.technology/portrait/header/549405-1724231193.jpg?lm=1",
      "shirtNumber": null
    },
    {
      "source": "transfermarkt-datasets",
      "sourcePlayerId": "1178536",
      "name": "Ville Nilsson",
      "position": "Attack",
      "detailedPosition": "Centre-Forward",
      "nationality": "Sweden",
      "dateOfBirth": "2004-06-12 00:00:00",
      "age": 22,
      "heightInCm": null,
      "currentClubName": "Kalmar Fotbollförening",
      "photoUrl": "https://img.a.transfermarkt.technology/portrait/header/default.jpg?lm=1",
      "shirtNumber": null
    },
    {
      "source": "transfermarkt-datasets",
      "sourcePlayerId": "638733",
      "name": "Aboubacar Keita",
      "position": "Defender",
      "detailedPosition": "Centre-Back",
      "nationality": "United States",
      "dateOfBirth": "2000-04-06 00:00:00",
      "age": 26,
      "heightInCm": 188,
      "currentClubName": "Kalmar Fotbollförening",
      "photoUrl": "https://img.a.transfermarkt.technology/portrait/header/638733-1678127447.jpg?lm=1",
      "shirtNumber": null
    },
    {
      "source": "transfermarkt-datasets",
      "sourcePlayerId": "566823",
      "name": "Achraf Dari",
      "position": "Defender",
      "detailedPosition": "Centre-Back",
      "nationality": "Morocco",
      "dateOfBirth": "1999-05-06 00:00:00",
      "age": 27,
      "heightInCm": 188,
      "currentClubName": "Kalmar Fotbollförening",
      "photoUrl": "https://img.a.transfermarkt.technology/portrait/header/566823-1736168954.jpg?lm=1",
      "shirtNumber": null
    },
    {
      "source": "transfermarkt-datasets",
      "sourcePlayerId": "128041",
      "name": "Lars Sætra",
      "position": "Defender",
      "detailedPosition": "Centre-Back",
      "nationality": "Norway",
      "dateOfBirth": "1991-07-24 00:00:00",
      "age": 34,
      "heightInCm": 195,
      "currentClubName": "Kalmar Fotbollförening",
      "photoUrl": "https://img.a.transfermarkt.technology/portrait/header/128041-1469086378.jpg?lm=1",
      "shirtNumber": null
    },
    {
      "source": "transfermarkt-datasets",
      "sourcePlayerId": "716897",
      "name": "Rony Jansson",
      "position": "Defender",
      "detailedPosition": "Right-Back",
      "nationality": "Finland",
      "dateOfBirth": "2004-01-10 00:00:00",
      "age": 22,
      "heightInCm": 183,
      "currentClubName": "Kalmar Fotbollförening",
      "photoUrl": "https://img.a.transfermarkt.technology/portrait/header/716897-1700727651.jpg?lm=1",
      "shirtNumber": null
    },
    {
      "source": "transfermarkt-datasets",
      "sourcePlayerId": "388646",
      "name": "Sivert Øverby",
      "position": "Defender",
      "detailedPosition": "Left-Back",
      "nationality": "Norway",
      "dateOfBirth": "1999-06-10 00:00:00",
      "age": 27,
      "heightInCm": 187,
      "currentClubName": "Kalmar Fotbollförening",
      "photoUrl": "https://img.a.transfermarkt.technology/portrait/header/default.jpg?lm=1",
      "shirtNumber": null
    },
    {
      "source": "transfermarkt-datasets",
      "sourcePlayerId": "1505734",
      "name": "Sodiq Lawal",
      "position": "Defender",
      "detailedPosition": "Left-Back",
      "nationality": "Nigeria",
      "dateOfBirth": "2008-01-14 00:00:00",
      "age": 18,
      "heightInCm": 178,
      "currentClubName": "Kalmar Fotbollförening",
      "photoUrl": "https://img.a.transfermarkt.technology/portrait/header/default.jpg?lm=1",
      "shirtNumber": null
    },
    {
      "source": "transfermarkt-datasets",
      "sourcePlayerId": "537221",
      "name": "Victor Larsson",
      "position": "Defender",
      "detailedPosition": "Centre-Back",
      "nationality": "Sweden",
      "dateOfBirth": "2000-04-19 00:00:00",
      "age": 26,
      "heightInCm": 183,
      "currentClubName": "Kalmar Fotbollförening",
      "photoUrl": "https://img.a.transfermarkt.technology/portrait/header/537221-1704806757.jpg?lm=1",
      "shirtNumber": null
    },
    {
      "source": "transfermarkt-datasets",
      "sourcePlayerId": "1235966",
      "name": "Zakarias Råvik",
      "position": "Defender",
      "detailedPosition": "Centre-Back",
      "nationality": "Sweden",
      "dateOfBirth": "2006-03-10 00:00:00",
      "age": 20,
      "heightInCm": null,
      "currentClubName": "Kalmar Fotbollförening",
      "photoUrl": "https://img.a.transfermarkt.technology/portrait/header/default.jpg?lm=1",
      "shirtNumber": null
    },
    {
      "source": "transfermarkt-datasets",
      "sourcePlayerId": "939246",
      "name": "Casper Andersson",
      "position": "Goalkeeper",
      "detailedPosition": "Goalkeeper",
      "nationality": "Sweden",
      "dateOfBirth": "2005-06-24 00:00:00",
      "age": 21,
      "heightInCm": 184,
      "currentClubName": "Kalmar Fotbollförening",
      "photoUrl": "https://img.a.transfermarkt.technology/portrait/header/default.jpg?lm=1",
      "shirtNumber": null
    },
    {
      "source": "transfermarkt-datasets",
      "sourcePlayerId": "554819",
      "name": "Jakob Kindberg",
      "position": "Goalkeeper",
      "detailedPosition": "Goalkeeper",
      "nationality": "Sweden",
      "dateOfBirth": "1994-02-07 00:00:00",
      "age": 32,
      "heightInCm": 184,
      "currentClubName": "Kalmar Fotbollförening",
      "photoUrl": "https://img.a.transfermarkt.technology/portrait/header/default.jpg?lm=1",
      "shirtNumber": null
    },
    {
      "source": "transfermarkt-datasets",
      "sourcePlayerId": "398971",
      "name": "Samuel Brolin",
      "position": "Goalkeeper",
      "detailedPosition": "Goalkeeper",
      "nationality": "Sweden",
      "dateOfBirth": "2000-09-29 00:00:00",
      "age": 25,
      "heightInCm": 202,
      "currentClubName": "Kalmar Fotbollförening",
      "photoUrl": "https://img.a.transfermarkt.technology/portrait/header/398971-1548408642.jpg?lm=1",
      "shirtNumber": null
    },
    {
      "source": "transfermarkt-datasets",
      "sourcePlayerId": "604859",
      "name": "Abdussalam Magashy",
      "position": "Midfield",
      "detailedPosition": "Attacking Midfield",
      "nationality": "Nigeria",
      "dateOfBirth": "1998-04-06 00:00:00",
      "age": 28,
      "heightInCm": 171,
      "currentClubName": "Kalmar Fotbollförening",
      "photoUrl": "https://img.a.transfermarkt.technology/portrait/header/604859-1725485555.jpg?lm=1",
      "shirtNumber": null
    },
    {
      "source": "transfermarkt-datasets",
      "sourcePlayerId": "430823",
      "name": "Carl Gustafsson",
      "position": "Midfield",
      "detailedPosition": "Central Midfield",
      "nationality": "Sweden",
      "dateOfBirth": "2000-03-18 00:00:00",
      "age": 26,
      "heightInCm": 180,
      "currentClubName": "Kalmar Fotbollförening",
      "photoUrl": "https://img.a.transfermarkt.technology/portrait/header/430823-1637671032.jpg?lm=1",
      "shirtNumber": null
    },
    {
      "source": "transfermarkt-datasets",
      "sourcePlayerId": "1519055",
      "name": "Elion Imeri",
      "position": "Midfield",
      "detailedPosition": "Attacking Midfield",
      "nationality": "Sweden",
      "dateOfBirth": "2009-06-21 00:00:00",
      "age": 17,
      "heightInCm": null,
      "currentClubName": "Kalmar Fotbollförening",
      "photoUrl": "https://img.a.transfermarkt.technology/portrait/header/default.jpg?lm=1",
      "shirtNumber": null
    },
    {
      "source": "transfermarkt-datasets",
      "sourcePlayerId": "909689",
      "name": "Marius Söderbäck",
      "position": "Midfield",
      "detailedPosition": "Attacking Midfield",
      "nationality": "Finland",
      "dateOfBirth": "2004-02-06 00:00:00",
      "age": 22,
      "heightInCm": 176,
      "currentClubName": "Kalmar Fotbollförening",
      "photoUrl": "https://img.a.transfermarkt.technology/portrait/header/909689-1779461803.jpg?lm=1",
      "shirtNumber": null
    },
    {
      "source": "transfermarkt-datasets",
      "sourcePlayerId": "203773",
      "name": "Melker Hallberg",
      "position": "Midfield",
      "detailedPosition": "Central Midfield",
      "nationality": "Sweden",
      "dateOfBirth": "1995-10-20 00:00:00",
      "age": 30,
      "heightInCm": 180,
      "currentClubName": "Kalmar Fotbollförening",
      "photoUrl": "https://img.a.transfermarkt.technology/portrait/header/203773-1624008999.jpg?lm=1",
      "shirtNumber": null
    },
    {
      "source": "transfermarkt-datasets",
      "sourcePlayerId": "646700",
      "name": "Nassef Chourak",
      "position": "Midfield",
      "detailedPosition": "Central Midfield",
      "nationality": "Netherlands",
      "dateOfBirth": "2004-07-21 00:00:00",
      "age": 21,
      "heightInCm": 185,
      "currentClubName": "Kalmar Fotbollförening",
      "photoUrl": "https://img.a.transfermarkt.technology/portrait/header/646700-1751545273.jpeg?lm=1",
      "shirtNumber": null
    },
    {
      "source": "transfermarkt-datasets",
      "sourcePlayerId": "187103",
      "name": "Robert Gojani",
      "position": "Midfield",
      "detailedPosition": "Central Midfield",
      "nationality": "Sweden",
      "dateOfBirth": "1992-10-19 00:00:00",
      "age": 33,
      "heightInCm": 174,
      "currentClubName": "Kalmar Fotbollförening",
      "photoUrl": "https://img.a.transfermarkt.technology/portrait/header/187103-1516981661.jpg?lm=1",
      "shirtNumber": null
    },
    {
      "source": "transfermarkt-datasets",
      "sourcePlayerId": "1164781",
      "name": "Vilmer Tyrén",
      "position": "Midfield",
      "detailedPosition": "Attacking Midfield",
      "nationality": "Sweden",
      "dateOfBirth": "2005-05-03 00:00:00",
      "age": 21,
      "heightInCm": 178,
      "currentClubName": "Kalmar Fotbollförening",
      "photoUrl": "https://img.a.transfermarkt.technology/portrait/header/default.jpg?lm=1",
      "shirtNumber": null
    },
    {
      "source": "transfermarkt-datasets",
      "sourcePlayerId": "1016312",
      "name": "William Andersson",
      "position": "Midfield",
      "detailedPosition": "Central Midfield",
      "nationality": "Sweden",
      "dateOfBirth": "2006-02-28 00:00:00",
      "age": 20,
      "heightInCm": null,
      "currentClubName": "Kalmar Fotbollförening",
      "photoUrl": "https://img.a.transfermarkt.technology/portrait/header/default.jpg?lm=1",
      "shirtNumber": null
    },
    {
      "source": "transfermarkt-datasets",
      "sourcePlayerId": "1093464",
      "name": "Wilmer Andersson",
      "position": "Missing",
      "detailedPosition": null,
      "nationality": "Sweden",
      "dateOfBirth": "2005-04-28 00:00:00",
      "age": 21,
      "heightInCm": 175,
      "currentClubName": "Kalmar Fotbollförening",
      "photoUrl": "https://img.a.transfermarkt.technology/portrait/header/default.jpg?lm=1",
      "shirtNumber": null
    }
  ]
}